LICENSE
README.md
setup.py
eme/__init__.py
eme/__websocket.py
eme/cli.py
eme/data_access.py
eme/entities.py
eme/static.py
eme/tcpserver.py
eme/tests.py
eme/website.py
eme/websocket.py
eme.egg-info/PKG-INFO
eme.egg-info/SOURCES.txt
eme.egg-info/dependency_links.txt
eme.egg-info/entry_points.txt
eme.egg-info/not-zip-safe
eme.egg-info/requires.txt
eme.egg-info/top_level.txt
eme/_tools/__init__.py
eme/_tools/cli.py
eme/_tools/commands/BundleCommand.py
eme/_tools/commands/EntityCommand.py
eme/_tools/commands/ModuleCommand.py
eme/_tools/commands/ScaffoldCommand.py
eme/_tools/content/command.tpl
eme/_tools/content/entity.tpl
eme/_tools/modules/easy_chat.zip
eme/_tools/modules/easy_mail.zip
eme/_tools/modules/easy_search.zip
eme/_tools/modules/eme_utils.zip
eme/_tools/modules/fe_boilerplate.zip
eme/_tools/modules/fe_boilerplate_bootstrap_native.zip
eme/_tools/modules/fe_boilerplate_bootstrap_vue.zip
eme/_tools/modules/users.zip
eme/plugins/__init__.py
eme/plugins/doors_oauth/__init__.py
eme/plugins/doors_oauth/__module__.py
eme/plugins/doors_oauth/controllers/UsersController.py
eme/plugins/doors_oauth/controllers/__init__.py
eme/plugins/doors_oauth/dal/__init__.py
eme/plugins/doors_oauth/dal/user_mixin.py
eme/plugins/doors_oauth/dal/user_repository.py
eme/plugins/doors_oauth/groups/UsersGroup.py
eme/plugins/doors_oauth/groups/__init__.py
eme/plugins/doors_oauth/services/__init__.py
eme/plugins/doors_oauth/services/auth.py
eme/plugins/doors_oauth/templates/doors/navbar_auth.html
eme/_tools/__init__.py
eme/_tools/cli.py
eme/_tools/commands/BundleCommand.py
eme/_tools/commands/EntityCommand.py
eme/_tools/commands/ModuleCommand.py
eme/_tools/commands/ScaffoldCommand.py
eme/_tools/content/command.tpl
eme/_tools/content/entity.tpl
eme/_tools/modules/easy_chat.zip
eme/_tools/modules/easy_mail.zip
eme/_tools/modules/easy_search.zip
eme/_tools/modules/eme_utils.zip
eme/_tools/modules/fe_boilerplate.zip
eme/_tools/modules/fe_boilerplate_bootstrap_native.zip
eme/_tools/modules/fe_boilerplate_bootstrap_vue.zip
eme/_tools/modules/users.zip
eme/plugins/__init__.py
eme/plugins/doors_oauth/__init__.py
eme/plugins/doors_oauth/__module__.py
