Metadata-Version: 2.1
Name: eme
Version: 5.2.3
Summary: Multi-purpose web framework
Home-page: https://github.com/oboforty/eme
Author: oboforty
Author-email: rajmund.csombordi@hotmail.com
License: MIT
Platform: UNKNOWN
License-File: LICENSE
